duds_converters/__init__.py
duds_converters/converter.py
duds_converters/utils.py
conversores_dudu-0.1.dist-info/METADATA
conversores_dudu-0.1.dist-info/WHEEL
conversores_dudu-0.1.dist-info/top_level.txt
conversores_dudu-0.1.dist-info/RECORD
