Metadata-Version: 2.1
Name: conversores_dudu
Version: 0.1
Requires-Dist: Pillow >=10.1.0
Requires-Dist: types-Pillow >=10.1.0.2
